jaywei_calculate_bmi_mcp/__init__.py
jaywei_calculate_bmi_mcp-0.1.0.dist-info/WHEEL
jaywei_calculate_bmi_mcp-0.1.0.dist-info/entry_points.txt
jaywei_calculate_bmi_mcp-0.1.0.dist-info/METADATA
jaywei_calculate_bmi_mcp-0.1.0.dist-info/RECORD
